tic_tac_toe_pygame/__init__.py
tic_tac_toe_pygame/__main__.py
tic_tac_toe_pygame/config.py
tic_tac_toe_pygame/event.py
tic_tac_toe_pygame/game.py
tic_tac_toe_pygame/state.py
tic_tac_toe_pygame-0.5.0.dist-info/LICENSE
tic_tac_toe_pygame-0.5.0.dist-info/METADATA
tic_tac_toe_pygame-0.5.0.dist-info/WHEEL
tic_tac_toe_pygame-0.5.0.dist-info/RECORD
