Metadata-Version: 2.1
Name: tic-tac-toe-pygame
Version: 0.5.0
Summary: A Python implementation of the Tic-Tac-Toe game using Pygame.
Home-page: https://github.com/giansimone/tic-tac-toe-pygame
License: MIT
Keywords: game,python,board-game,tic-tac-toe,pygame,python3,tic-tac-toe-game,tic-tac-toe-python
Author: Giansimone Perrino
Author-email: hello@giansimone.dev
Requires-Python: >=3.10,<4.0
Classifier: Development Status :: 4 - Beta
Classifier: Intended Audience :: End Users/Desktop
Classifier: License :: OSI Approved :: MIT License
Classifier: Operating System :: OS Independent
Classifier: Programming Language :: Python :: 3
Classifier: Programming Language :: Python :: 3.10
Classifier: Programming Language :: Python :: 3.11
Classifier: Programming Language :: Python :: 3.12
Classifier: Programming Language :: Python :: 3.13
Classifier: Topic :: Games/Entertainment
Classifier: Topic :: Software Development :: Libraries
Requires-Dist: pygame (>=2.6.1,<3.0.0)
Project-URL: Repository, https://github.com/giansimone/tic-tac-toe-pygame
